{"General Information":{"name":"Jonas Sievers","email":"jonas.sievers@kit.edu"},"education":[{"institution":"Karlsruhe Institute of Technology, Karlsruhe, Germany","url":"https://www.kit.edu/english/index.php","area":"Machine Learning","studyType":"PhD","startDate":"2022-08-01","endDate":"2025-07-31"}],"Experience":[{"title":"Nobel Prize in Physics","date":"1921-11-01","awarder":"Royal Swedish Academy of Sciences","summary":"The Nobel Prizes are five separate prizes that, according to Alfred Nobel's will of 1895, are awarded to 'those who, during the preceding year, have conferred the greatest benefit to humankind.'"}],"Honors and Awards":[{"title":"Nobel Prize in Physics","date":"1921-11-01","awarder":"Royal Swedish Academy of Sciences","summary":"The Nobel Prizes are five separate prizes that, according to Alfred Nobel's will of 1895, are awarded to 'those who, during the preceding year, have conferred the greatest benefit to humankind.'"}]}